{
  "indexes": [
    {
      "collectionGroup": "calls",
      "queryScope": "COLLECTION_GROUP",
      "fields": [
        {
          "fieldPath": "receiverId",
          "order": "ASCENDING"
        },
        {
          "fieldPath": "status",
          "order": "ASCENDING"
        },
        {
          "fieldPath": "__name__",
          "order": "ASCENDING"
        }
      ]
    },
    {
      "collectionGroup": "messages",
      "queryScope": "COLLECTION",
      "fields": [
        {
          "fieldPath": "isRead",
          "order": "ASCENDING"
        },
        {
          "fieldPath": "senderId",
          "order": "ASCENDING"
        },
        {
          "fieldPath": "__name__",
          "order": "ASCENDING"
        }
      ]
    },
    {
      "collectionGroup": "emergency_alerts",
      "queryScope": "COLLECTION",
      "fields": [
        {
          "fieldPath": "acceptedBy",
          "order": "ASCENDING"
        },
        {
          "fieldPath": "status",
          "order": "ASCENDING"
        },
        {
          "fieldPath": "createdAt",
          "order": "DESCENDING"
        }
      ]
    },
    {
      "collectionGroup": "emergency_alerts",
      "queryScope": "COLLECTION",
      "fields": [
        {
          "fieldPath": "acceptedBy",
          "order": "ASCENDING"
        },
        {
          "fieldPath": "status",
          "order": "ASCENDING"
        },
        {
          "fieldPath": "acceptedAt",
          "order": "DESCENDING"
        }
      ]
    },
    {
      "collectionGroup": "emergency_alerts",
      "queryScope": "COLLECTION",
      "fields": [
        {
          "fieldPath": "userId",
          "order": "ASCENDING"
        },
        {
          "fieldPath": "status",
          "order": "ASCENDING"
        },
        {
          "fieldPath": "createdAt",
          "order": "DESCENDING"
        }
      ]
    },
    {
      "collectionGroup": "emergency_alerts",
      "queryScope": "COLLECTION",
      "fields": [
        {
          "fieldPath": "status",
          "order": "ASCENDING"
        },
        {
          "fieldPath": "createdAt",
          "order": "ASCENDING"
        }
      ]
    }
  ],
  "fieldOverrides": []
}
